{
    "version":  "1.0.1",
    "releaseDate":  "2026-06-02",
    "releaseNotes":  "# DPX AppDock 1.0.1\r\n\r\nRelease date: 2026-06-02\r\n\r\nBug fixes and polish for dock groups, placement, and drag-and-drop.\r\n\r\n## Group dock\r\n\r\n- Expanded group panel **centers on the group icon** (static callout arrow)\r\n- **Reorder animations** when dragging shortcuts inside an expanded group\r\n- Group panel **stays open** while dragging items into the group (from the main dock or Explorer)\r\n- **Drop from Explorer** directly onto the expanded group panel\r\n- **Folder badge** on collapsed group icons\r\n\r\n## Dock \u0026 UI\r\n\r\n- **Along-edge placement** slider (0–100%) in Settings → Position\r\n- Settings, edit-group, and confirm dialogs open **beside the dock**, not over it\r\n- Improved group expand positioning and focus handling during drags\r\n\r\n## Install \u0026 update\r\n\r\n- **Setup:** `DPX.AppDock-1.0.1-setup.exe`\r\n- **In-app update package:** `DPX.AppDock-1.0.1-win-x64.zip`\r\n- Publish instructions: [RELEASE.md](RELEASE.md)\r\n",
    "downloadUrl":  "https://github.com/0xDPX/dpx-appdock-releases/releases/download/v1.0.1/DPX.AppDock-1.0.1-win-x64.zip",
    "mandatory":  false,
    "sha256":  "8eee1b990b26c7409c7c824b7afa624f99e2513113695a30b33ec38a47397e8b"
}

